particular/__init__.py
particular/main.py
particular-0.1.4.dist-info/LICENSE
particular-0.1.4.dist-info/METADATA
particular-0.1.4.dist-info/WHEEL
particular-0.1.4.dist-info/entry_points.txt
particular-0.1.4.dist-info/top_level.txt
particular-0.1.4.dist-info/RECORD
